liveaudio/LinearVolumeNormalizer.py
liveaudio/LivePyin.py
liveaudio/PitchShiftVocoder.py
liveaudio/__init__.py
liveaudio/buffers.py
liveaudio/realtimeHmm.py
liveaudio/utils.py
liveaudio-0.0.8.dist-info/licenses/LICENSE
liveaudio-0.0.8.dist-info/METADATA
liveaudio-0.0.8.dist-info/WHEEL
liveaudio-0.0.8.dist-info/top_level.txt
liveaudio-0.0.8.dist-info/RECORD
