Metadata-Version: 2.4
Name: liveaudio
Version: 0.0.8
Summary: Real-time audio processing library based on librosa
Home-page: https://github.com/gabiteodoru/liveaudio
Author: Gabi Teodoru
Author-email: gabiteodoru@gmail.com
License: MIT
Project-URL: Bug Tracker, https://github.com/gabiteodoru/liveaudio/issues
Project-URL: Source Code, https://github.com/gabiteodoru/liveaudio
Classifier: Programming Language :: Python :: 3
Classifier: Operating System :: OS Independent
Requires-Python: >=3.6
License-File: LICENSE
Requires-Dist: numpy>=2.2.4
Requires-Dist: numba>=0.61.2
Requires-Dist: scipy>=1.15.2
Requires-Dist: librosa>=0.11.0
Provides-Extra: dev
Requires-Dist: pytest>=7.0.0; extra == "dev"
Dynamic: license-file
